lessllm/__init__.py
lessllm/cli.py
lessllm/config.py
lessllm/server.py
lessllm/logging/__init__.py
lessllm/logging/logger.py
lessllm/logging/models.py
lessllm/logging/storage.py
lessllm/monitoring/__init__.py
lessllm/monitoring/cache_estimator.py
lessllm/monitoring/performance.py
lessllm/providers/__init__.py
lessllm/providers/base.py
lessllm/providers/claude.py
lessllm/providers/openai.py
lessllm/proxy/__init__.py
lessllm/proxy/manager.py
lessllm/utils/__init__.py
lessllm/utils/cost_calculator.py
lessllm/utils/token_counter.py
lessllm-0.2.0.dist-info/METADATA
lessllm-0.2.0.dist-info/WHEEL
lessllm-0.2.0.dist-info/entry_points.txt
lessllm-0.2.0.dist-info/licenses/LICENSE
lessllm-0.2.0.dist-info/RECORD
